karanage/__init__.py
karanage/connection.py
karanage/exception.py
karanage/log.py
karanage/py.typed
karanage/state.py
karanage-0.7.3.dist-info/COPYING
karanage-0.7.3.dist-info/METADATA
karanage-0.7.3.dist-info/WHEEL
karanage-0.7.3.dist-info/top_level.txt
karanage-0.7.3.dist-info/RECORD
